pythondata_cpu_cv32e40s/__init__.py
pythondata_cpu_cv32e40s/system_verilog/.dir-locals.el
pythondata_cpu_cv32e40s/system_verilog/.gitignore
pythondata_cpu_cv32e40s/system_verilog/CONTRIBUTING.md
pythondata_cpu_cv32e40s/system_verilog/LICENSE
pythondata_cpu_cv32e40s/system_verilog/README.md
pythondata_cpu_cv32e40s/system_verilog/cv32e40s_manifest.flist
pythondata_cpu_cv32e40s/system_verilog/.github/release.yml
pythondata_cpu_cv32e40s/system_verilog/.github/ISSUE_TEMPLATE/bug.md
pythondata_cpu_cv32e40s/system_verilog/.github/ISSUE_TEMPLATE/config.yml
pythondata_cpu_cv32e40s/system_verilog/.github/ISSUE_TEMPLATE/enhancement.md
pythondata_cpu_cv32e40s/system_verilog/.github/ISSUE_TEMPLATE/question.md
pythondata_cpu_cv32e40s/system_verilog/.github/ISSUE_TEMPLATE/task.md
pythondata_cpu_cv32e40s/system_verilog/bhv/cv32e40s_core_log.sv
pythondata_cpu_cv32e40s/system_verilog/bhv/cv32e40s_dbg_helper.sv
pythondata_cpu_cv32e40s/system_verilog/bhv/cv32e40s_rvfi.sv
pythondata_cpu_cv32e40s/system_verilog/bhv/cv32e40s_rvfi_data_obi.sv
pythondata_cpu_cv32e40s/system_verilog/bhv/cv32e40s_rvfi_instr_obi.sv
pythondata_cpu_cv32e40s/system_verilog/bhv/cv32e40s_sim_clock_gate.sv
pythondata_cpu_cv32e40s/system_verilog/bhv/cv32e40s_sim_sffr.sv
pythondata_cpu_cv32e40s/system_verilog/bhv/cv32e40s_sim_sffs.sv
pythondata_cpu_cv32e40s/system_verilog/bhv/cv32e40s_wrapper.sv
pythondata_cpu_cv32e40s/system_verilog/bhv/rvfi_sim_trace.sv
pythondata_cpu_cv32e40s/system_verilog/bhv/include/cv32e40s_rvfi_pkg.sv
pythondata_cpu_cv32e40s/system_verilog/bhv/include/cv32e40s_wrapper.vh
pythondata_cpu_cv32e40s/system_verilog/constraints/cv32e40s_core.sdc
pythondata_cpu_cv32e40s/system_verilog/docs/.gitkeep
pythondata_cpu_cv32e40s/system_verilog/docs/user_manual/.gitignore
pythondata_cpu_cv32e40s/system_verilog/docs/user_manual/Makefile
pythondata_cpu_cv32e40s/system_verilog/docs/user_manual/make.bat
pythondata_cpu_cv32e40s/system_verilog/docs/user_manual/requirements.txt
pythondata_cpu_cv32e40s-0.6.0.post175.dist-info/LICENSE
pythondata_cpu_cv32e40s-0.6.0.post175.dist-info/METADATA
pythondata_cpu_cv32e40s-0.6.0.post175.dist-info/WHEEL
pythondata_cpu_cv32e40s-0.6.0.post175.dist-info/top_level.txt
pythondata_cpu_cv32e40s-0.6.0.post175.dist-info/RECORD
