Metadata-Version: 2.1
Name: pythondata-cpu-cv32e40s
Version: 0.6.0.post175
Summary: Python module containing system_verilog files for CV32E40S cpu.
Home-page: https://github.com/litex-hub/pythondata-cpu-cv32e40s
Author: LiteX Authors
Author-email: litex@googlegroups.com
Project-URL: Bug Tracker, https://github.com/litex-hub/pythondata-cpu-cv32e40s/issues
Project-URL: Source Code, https://github.com/litex-hub/pythondata-cpu-cv32e40s
Classifier: Programming Language :: Python :: 3
Classifier: License :: OSI Approved :: Apache Software License
Classifier: Operating System :: OS Independent
Requires-Python: >=3.5
License-File: LICENSE
